mps_conv3d/_C.cpython-314-darwin.so
mps_conv3d/__init__.py
mps_conv3d/csrc/conv3d_mps.mm
mps_conv3d-0.1.5.dist-info/METADATA
mps_conv3d-0.1.5.dist-info/WHEEL
mps_conv3d-0.1.5.dist-info/top_level.txt
mps_conv3d-0.1.5.dist-info/RECORD
