Metadata-Version: 2.4
Name: mps-conv3d
Version: 0.1.5
Summary: 3D Convolution for Apple Silicon (MPS)
Author: mpsops
License-Expression: MIT
Project-URL: Homepage, https://github.com/mpsops/mps-conv3d
Project-URL: Repository, https://github.com/mpsops/mps-conv3d
Project-URL: Issues, https://github.com/mpsops/mps-conv3d/issues
Keywords: pytorch,mps,apple-silicon,conv3d,video,3d-convolution
Classifier: Development Status :: 4 - Beta
Classifier: Intended Audience :: Developers
Classifier: Intended Audience :: Science/Research
Classifier: Operating System :: MacOS :: MacOS X
Classifier: Programming Language :: Python :: 3
Classifier: Programming Language :: Python :: 3.10
Classifier: Programming Language :: Python :: 3.11
Classifier: Programming Language :: Python :: 3.12
Classifier: Topic :: Scientific/Engineering :: Artificial Intelligence
Requires-Python: >=3.10
Requires-Dist: torch>=2.0.0
Dynamic: requires-python
